{
  "translation": "CSP",
  "translation_name": "Český studijní překlad",
  "book": "PSA",
  "book_name": "Žalmy",
  "book_abbr": "Ž",
  "chapter": 6,
  "verses": {
    "1": "Kéž se radují všichni, kteří v tobě mají útočiště. Navěky budou jásat a ty je budeš chránit. Kéž se z tebe veselí ti, kdo milují tvé jméno!",
    "2": "Vždyť ty, Hospodine, žehnáš spravedlivému, jako pavézou ho obklopuješ přízní!",
    "3": "",
    "4": "Pro vedoucího chval. ⌈Na strunné nástroje⌉ k ⌈nízkému zpěvu⌉. Davidův žalm.",
    "5": "Hospodine, nekárej mě ve svém hněvu, ve své zlobě mě nekázni!",
    "6": "Smiluj se nade mnou, Hospodine, neboť jsem zemdlený! Uzdrav mě, Hospodine, vždyť mé kosti se třesou!",
    "7": "I má duše je velmi vyděšená. A ty, Hospodine, až dokdy?",
    "8": "Navrať se, Hospodine, vytrhni mou duši, zachraň mě pro své milosrdenství!",
    "9": "⌈Mezi mrtvými na tebe nikdo nevzpomíná!⌉ Kdo by ti vzdával chválu v podsvětí?",
    "10": "Jsem vyčerpán svým vzdycháním. Každé noci promáčím své lůžko, slzami svou postel rozmočím."
  },
  "copyright": "© Nakladatelství KMS, s.r.o. Licence: Creative Commons BY-NC-ND 4.0. Text neupravujte; používejte pouze nekomerčně a s uvedením licence."
}