{
  "translation": "CSP",
  "translation_name": "Český studijní překlad",
  "book": "PRO",
  "book_name": "Přísloví",
  "book_abbr": "Př",
  "chapter": 26,
  "verses": {
    "1": "Neodpovídej hlupákovi podle jeho hlouposti, jinak ⌈budeš jako on.⌉",
    "2": "Odpověz hlupákovi podle jeho hlouposti, jinak ⌈bude moudrý ve svých očích.⌉",
    "3": "Kdo posílá poselství po hlupákovi, je jako ten, kdo si usekává nohy a pije násilí.",
    "4": "Jako volně visí nohy chromého, tak je přísloví v ústech hlupáků.",
    "5": "⌈Jako přivázat kámen k praku, takové je dát hlupákovi slávu.⌉",
    "6": "Jako trní, které se dostalo do ruky opilce, tak je přísloví v ústech hlupáků.",
    "7": "⌈Jako lukostřelec, který každého zraňuje, je ten,⌉ kdo najímá hlupáka, kdo najímá kolemjdoucí.",
    "8": "Jako se pes navrací ke svému zvratku, tak hlupák opakuje svoji hloupost.",
    "9": "Viděl jsi člověka ⌈moudrého ve svých očích?⌉ Pro hlupáka je víc naděje než pro něj!",
    "10": "Lenoch říká: Lev je na cestě, lev je v ulicích!",
    "11": "Jako se dveře otáčejí na svém pantu, tak lenoch na své posteli.",
    "12": "Lenoch ponoří svou ruku do mísy a je mu zatěžko zvednout ji do svých úst.",
    "13": "Lenoch ⌈je moudřejší ve svých očích⌉ než sedm lidí, kteří rozvážně odpovídají.",
    "14": "Kdo prochází kolem a nazlobí se kvůli sporu, který se ho netýká, je jako ten, kdo chytá psa za uši.",
    "15": "Jako šílenec, který střílí ohnivé střely a ⌈smrtící šípy,⌉",
    "16": "je člověk, který podvede svého bližního a potom řekne: Já jsem jenom vtipkoval.",
    "17": "Kde není dostatek dřeva, oheň uhasne, kde není pomlouvač, utichne svár.",
    "18": "Uhlí na žár, dřevo na oheň, svárlivý člověk pro zažehnutí sporu.",
    "19": "Slova pomlouvače jsou jako pamlsky, ⌈sestupují do nejzazších útrob.⌉",
    "20": "Jako stříbrná glazura potažená na hliněnou nádobu jsou horoucí rty a zlé srdce.",
    "21": "Ten, kdo nenávidí, ⌈to svými rty zastírá,⌉ ale ve svém nitru ⌈připravuje podvod.⌉",
    "22": "I když bude ⌈jeho hlas vlídný, nevěř mu, protože v jeho srdci je sedm ohavností.",
    "23": "Jeho nenávist může být zakryta lstivostí, ale jeho zlo se zjeví ve shromáždění.",
    "24": "Kdo kope jámu, spadne do ní, kdo valí kámen, na něj se obrátí.",
    "25": "Lživý jazyk nenávidí ty, které utlačuje, lichotivá ústa působí zkázu.",
    "26": "",
    "27": "Nechlub se zítřejším dnem, neboť nevíš, co den přinese.",
    "28": "Ať tě chválí někdo jiný, a ne tvoje ústa, někdo cizí, a ne tvoje rty."
  },
  "copyright": "© Nakladatelství KMS, s.r.o. Licence: Creative Commons BY-NC-ND 4.0. Text neupravujte; používejte pouze nekomerčně a s uvedením licence."
}